{
  "dict": {
    "auto_detect": "yes",
    "customize": {
      "check_that_exists": "yes",
      "env_prefix": "CK_ENV_LIB_TENSORRT",
      "limit_recursion_dir_search": {
        "linux": 3
      },
      "soft_file": {
        "linux": "libnvinfer.so"
      }
    },
    "soft_name": "TensorRT engine",
    "tags": [
      "lib",
      "tensorrt",
      "inference"
    ]
  },
  "misc": {
    "auto_detect": "yes",
    "data_uid": "63257b98ef23405c",
    "data_uoa": "lib.tensorrt",
    "env_prefix": "CK_ENV_LIB_TENSORRT",
    "host_os": "any",
    "module_uid": "5e1100048ab875d7",
    "module_uoa": "soft",
    "repo_uid": "3abe4a16a4fb17d7",
    "repo_uoa": "ck-tensorrt",
    "repo_url1": "",
    "repo_url2": "http://github.com/ctuning/ck-tensorrt/tree/master/soft/lib.tensorrt/.cm/meta.json",
    "repo_url3": "http://github.com/ctuning/ck-tensorrt/tree/master/soft/lib.tensorrt",
    "soft_name": "TensorRT engine",
    "stags": "lib,tensorrt,inference",
    "tags": [
      "lib",
      "tensorrt",
      "inference"
    ],
    "target_os": "any",
    "template": "",
    "to_get": "ck pull repo:ck-tensorrt"
  }
}
